clp2qr.py
clp2qr-1.0.0.dist-info/METADATA
clp2qr-1.0.0.dist-info/WHEEL
clp2qr-1.0.0.dist-info/top_level.txt
clp2qr-1.0.0.dist-info/RECORD
