Metadata-Version: 2.1
Name: clp2qr
Version: 1.0.0
Summary: Clipboard to QR
Home-page: UNKNOWN
License: MIT
Platform: UNKNOWN
Requires-Dist: pywin32 (==306)
Requires-Dist: qrcode (==7.4.2)
Requires-Dist: qreader (==3.14)
